tests/__init__.py
tests/not_set.py
tests/test_ansi.py
tests/test_enum.py
tests/test_frozen.py
tests/test_io.py
tests/test_singleton.py
tests/log/__init__.py
tests/log/base.py
tests/log/test_cute.py
tests/log/test_trace.py
zstdlib/__init__.py
zstdlib/ansi.py
zstdlib/enum.py
zstdlib/frozen.py
zstdlib/io.py
zstdlib/not_set.py
zstdlib/py.typed
zstdlib/singleton.py
zstdlib/log/__init__.py
zstdlib/log/cute.py
zstdlib/log/trace.py
zstdlib-0.2.0.dist-info/licenses/LICENSE
zstdlib-0.2.0.dist-info/METADATA
zstdlib-0.2.0.dist-info/WHEEL
zstdlib-0.2.0.dist-info/top_level.txt
zstdlib-0.2.0.dist-info/RECORD
