Metadata-Version: 2.4
Name: zstdlib
Version: 0.2.0
Summary: A set of useful python utilities
License: GPLv3
Project-URL: Homepage, https://github.com/zwimer/zstdlib
Keywords: remote,pipe
Classifier: Programming Language :: Python :: 3
Classifier: Programming Language :: Python :: 3.12
Classifier: Development Status :: 5 - Production/Stable
Classifier: License :: OSI Approved :: GNU General Public License v3 (GPLv3)
Requires-Python: >=3.12
License-File: LICENSE
Dynamic: license-file
